ipanemap/__init__.py
ipanemap/__main__.py
ipanemap/clustering.py
ipanemap/clusters_trait.py
ipanemap/conf.py
ipanemap/file_functions.py
ipanemap/optimize_clustering.py
ipanemap/pipeline.py
ipanemap/progress.py
ipanemap/sampling.py
ipanemap/structure_functions.py
ipanemap/visualization_tools.py
ipanemap-0.1.6.dist-info/METADATA
ipanemap-0.1.6.dist-info/WHEEL
ipanemap-0.1.6.dist-info/entry_points.txt
ipanemap-0.1.6.dist-info/top_level.txt
ipanemap-0.1.6.dist-info/RECORD
