Metadata-Version: 2.1
Name: ipanemap
Version: 0.1.6
Summary: integrative probing analysis of nucleic acids empowered by multiple accessibility profiles
Keywords: RNA,folding,bioinformatics,RNAFold,ViennaRNA
Classifier: Programming Language :: Python :: 3
Classifier: License :: OSI Approved :: GNU General Public License v3 (GPLv3)
Requires-Dist: wheel
Requires-Dist: cython
Requires-Dist: scipy
Requires-Dist: numpy
Requires-Dist: sklearn
Requires-Dist: pyyaml
Requires-Dist: matplotlib
